atomnlp.py
atomicnlp-0.0.1a1.dist-info/METADATA
atomicnlp-0.0.1a1.dist-info/WHEEL
atomicnlp-0.0.1a1.dist-info/entry_points.txt
atomicnlp-0.0.1a1.dist-info/top_level.txt
atomicnlp-0.0.1a1.dist-info/RECORD
